flask_inflate.py
Flask_Inflate-0.3.dist-info/LICENSE
Flask_Inflate-0.3.dist-info/METADATA
Flask_Inflate-0.3.dist-info/WHEEL
Flask_Inflate-0.3.dist-info/top_level.txt
Flask_Inflate-0.3.dist-info/RECORD
